nx_io/__init__.py
nx_io/open_file.py
nx_io/readlines.py
nx_io/version.txt
nx_io-3.0.3.dist-info/DESCRIPTION.rst
nx_io-3.0.3.dist-info/METADATA
nx_io-3.0.3.dist-info/RECORD
nx_io-3.0.3.dist-info/WHEEL
nx_io-3.0.3.dist-info/metadata.json
nx_io-3.0.3.dist-info/top_level.txt
tests/__init__.py
tests/test_open_file.py
tests/test_readlines.py
