Metadata-Version: 2.0
Name: nx-io
Version: 3.0.3
Summary: Miscellaneous I/O utilities
Home-page: https://github.com/nxdevel/nx_io
Author: A Bradford
Author-email: nxdevel@users.noreply.github.com
License: MIT
Keywords: development utilities io readline
Platform: UNKNOWN
Classifier: Development Status :: 5 - Production/Stable
Classifier: License :: OSI Approved :: MIT License
Classifier: Programming Language :: Python :: 3 :: Only
Classifier: Topic :: Software Development :: Libraries
Classifier: Topic :: Utilities
Classifier: Intended Audience :: Developers
